erpbrasil.edoc-3.1.0-py3.10-nspkg.pth
erpbrasil/edoc/__main__.py
erpbrasil/edoc/chave.py
erpbrasil/edoc/cli.py
erpbrasil/edoc/cte.py
erpbrasil/edoc/edoc.py
erpbrasil/edoc/mde.py
erpbrasil/edoc/mdfe.py
erpbrasil/edoc/nfce.py
erpbrasil/edoc/nfe.py
erpbrasil/edoc/nfse.py
erpbrasil/edoc/resposta.py
erpbrasil/edoc/provedores/__init__.py
erpbrasil/edoc/provedores/barueri.py
erpbrasil/edoc/provedores/cidades.py
erpbrasil/edoc/provedores/dsf.py
erpbrasil/edoc/provedores/ginfes.py
erpbrasil/edoc/provedores/issnet.py
erpbrasil/edoc/provedores/paulistana.py
erpbrasil/nfelib_legacy/__init__.py
erpbrasil/nfelib_legacy/v4_00/README.txt
erpbrasil/nfelib_legacy/v4_00/__init__.py
erpbrasil/nfelib_legacy/v4_00/distDFeInt.py
erpbrasil/nfelib_legacy/v4_00/leiauteNFe_sub.py
erpbrasil/nfelib_legacy/v4_00/retConsCad.py
erpbrasil/nfelib_legacy/v4_00/retConsReciNFe.py
erpbrasil/nfelib_legacy/v4_00/retConsSitNFe.py
erpbrasil/nfelib_legacy/v4_00/retConsStatServ.py
erpbrasil/nfelib_legacy/v4_00/retDistDFeInt.py
erpbrasil/nfelib_legacy/v4_00/retEnvCCe.py
erpbrasil/nfelib_legacy/v4_00/retEnvConfRecebto.py
erpbrasil/nfelib_legacy/v4_00/retEnvEvento.py
erpbrasil/nfelib_legacy/v4_00/retEnvEventoCancNFe.py
erpbrasil/nfelib_legacy/v4_00/retEnviNFe.py
erpbrasil/nfelib_legacy/v4_00/retInutNFe.py
erpbrasil_edoc-3.1.0.dist-info/licenses/AUTHORS.rst
erpbrasil_edoc-3.1.0.dist-info/licenses/LICENSE
erpbrasil_edoc-3.1.0.dist-info/METADATA
erpbrasil_edoc-3.1.0.dist-info/WHEEL
erpbrasil_edoc-3.1.0.dist-info/entry_points.txt
erpbrasil_edoc-3.1.0.dist-info/namespace_packages.txt
erpbrasil_edoc-3.1.0.dist-info/top_level.txt
erpbrasil_edoc-3.1.0.dist-info/RECORD
