Metadata-Version: 2.4
Name: erpbrasil.edoc
Version: 3.1.0
Summary: Emissão de documentos fiscais e outras obrigações (NF-E, NFS-E, MDF-E, CT-E, REINF, E-SOCIAL)
Home-page: https://github.com/erpbrasil/erpbrasil.edoc
Author: Luis Felipe Mileo
Author-email: mileo@kmee.com.br
License: MIT
Project-URL: Documentation, https://erpbrasiledoc.readthedocs.io/
Project-URL: Changelog, https://erpbrasiledoc.readthedocs.io/en/latest/changelog.html
Project-URL: Issue Tracker, https://github.com/erpbrasil/erpbrasil.edoc/issues
Classifier: Development Status :: 5 - Production/Stable
Classifier: Intended Audience :: Developers
Classifier: License :: OSI Approved :: MIT License
Classifier: Operating System :: Unix
Classifier: Operating System :: POSIX
Classifier: Operating System :: Microsoft :: Windows
Classifier: Programming Language :: Python
Classifier: Programming Language :: Python :: 3
Classifier: Programming Language :: Python :: 3.5
Classifier: Programming Language :: Python :: 3.6
Classifier: Programming Language :: Python :: 3.7
Classifier: Programming Language :: Python :: Implementation :: CPython
Classifier: Programming Language :: Python :: Implementation :: PyPy
Classifier: Topic :: Utilities
Requires-Python: >=3.5, !=3.0.*, !=3.1.*, !=3.2.*, !=3.3.*
License-File: LICENSE
License-File: AUTHORS.rst
Requires-Dist: erpbrasil.base>=2.0.0
Requires-Dist: erpbrasil.assinatura>=1.2.0
Requires-Dist: erpbrasil.transmissao>=1.0.0
Provides-Extra: nfselib-ginfes
Requires-Dist: nfselib.ginfes; extra == "nfselib-ginfes"
Provides-Extra: nfselib-paulistana
Requires-Dist: nfselib.paulistana; extra == "nfselib-paulistana"
Provides-Extra: nfselib-dsf
Requires-Dist: nfselib.dsf; extra == "nfselib-dsf"
Provides-Extra: nfselib-betha
Requires-Dist: nfselib.betha; extra == "nfselib-betha"
Provides-Extra: nfselib-issnet
Requires-Dist: nfselib.issnet; extra == "nfselib-issnet"
Provides-Extra: nfelib
Requires-Dist: nfselib; extra == "nfelib"
Provides-Extra: mdfelib
Requires-Dist: mdfelib; extra == "mdfelib"
Dynamic: author
Dynamic: author-email
Dynamic: classifier
Dynamic: description
Dynamic: home-page
Dynamic: license
Dynamic: license-file
Dynamic: project-url
Dynamic: provides-extra
Dynamic: requires-dist
Dynamic: requires-python
Dynamic: summary
